py_talk_ex-1.6.2.dist-info/licenses/LICENSE
pytalk/__init__.py
pytalk/_utils.py
pytalk/audio.py
pytalk/backoff.py
pytalk/bot.py
pytalk/channel.py
pytalk/codec.py
pytalk/device.py
pytalk/download_sdk.py
pytalk/enums.py
pytalk/exceptions.py
pytalk/instance.py
pytalk/message.py
pytalk/permission.py
pytalk/server.py
pytalk/statistics.py
pytalk/streamer.py
pytalk/subscription.py
pytalk/tt_file.py
pytalk/user.py
pytalk/user_account.py
pytalk/implementation/__init__.py
pytalk/tools/__init__.py
pytalk/tools/downloader.py
pytalk/tools/ttsdk_downloader.py
py_talk_ex-1.6.2.dist-info/METADATA
py_talk_ex-1.6.2.dist-info/WHEEL
py_talk_ex-1.6.2.dist-info/top_level.txt
py_talk_ex-1.6.2.dist-info/RECORD
